mnist_dnn/__init__.py
mnist_dnn/__main__.py
mnist_dnn/dataset.py
mnist_dnn/layer.py
mnist_dnn/model.py
mnist_dnn/core/__init__.py
mnist_dnn/core/encoder.py
mnist_dnn/core/activation_function/__init__.py
mnist_dnn/core/activation_function/relu.py
mnist_dnn/core/activation_function/softmax.py
mnist_dnn/core/layer/__init__.py
mnist_dnn/core/layer/activation.py
mnist_dnn/core/layer/base.py
mnist_dnn/core/layer/dendrite.py
mnist_dnn/core/loss_function/__init__.py
mnist_dnn/core/loss_function/categorical_crossentropy.py
mnist_dnn/core/optimizer/__init__.py
mnist_dnn/core/optimizer/gradient_descent.py
mnist_dnn/data/mnist_test.csv
mnist_dnn/data/mnist_train.csv
mnist_dnn/util/__init__.py
mnist_dnn/util/tool.py
mnist_dnn-0.1.3.dist-info/LICENSE
mnist_dnn-0.1.3.dist-info/METADATA
mnist_dnn-0.1.3.dist-info/WHEEL
mnist_dnn-0.1.3.dist-info/top_level.txt
mnist_dnn-0.1.3.dist-info/RECORD
