Metadata-Version: 2.1
Name: mnist-dnn
Version: 0.1.3
Summary: Deep Neural Network from Scratch with MNIST dataset
Home-page: https://github.com/fedele7008/MNIST_DNN
Author: John Yoon
Author-email: fedelejohn7008@gmail.com
Project-URL: Issue Tracker, https://github.com/fedele7008/MNIST_DNN/issues
Project-URL: Wiki, https://github.com/fedele7008/MNIST_DNN/wiki
Classifier: Programming Language :: Python :: 3
Classifier: Programming Language :: Python :: 3.6
Classifier: Programming Language :: Python :: 3.11
Classifier: License :: OSI Approved :: MIT License
Requires-Python: >=3.6
License-File: LICENSE
Requires-Dist: colorama (==0.4.6)
Requires-Dist: contourpy (==1.0.7)
Requires-Dist: cycler (==0.11.0)
Requires-Dist: exceptiongroup (==1.1.1)
Requires-Dist: fonttools (==4.38.0)
Requires-Dist: iniconfig (==2.0.0)
Requires-Dist: kiwisolver (==1.4.4)
Requires-Dist: llvmlite (==0.39.1)
Requires-Dist: matplotlib (==3.6.3)
Requires-Dist: numba (==0.56.4)
Requires-Dist: numpy (==1.23.5)
Requires-Dist: opencv-python (==4.7.0.72)
Requires-Dist: packaging (==23.0)
Requires-Dist: pandas (==1.5.2)
Requires-Dist: Pillow (==9.4.0)
Requires-Dist: pluggy (==1.0.0)
Requires-Dist: py (==1.11.0)
Requires-Dist: pyparsing (==3.0.9)
Requires-Dist: pytest (==7.3.1)
Requires-Dist: pytest-html (==3.2.0)
Requires-Dist: pytest-metadata (==2.0.4)
Requires-Dist: python-dateutil (==2.8.2)
Requires-Dist: pytz (==2022.7.1)
Requires-Dist: six (==1.16.0)
Requires-Dist: tomli (==2.0.1)
